LICENSE.txt
MANIFEST.in
glibc.py
icu_sources.py
pep425tags.py
requirements.txt
setup.cfg
setup.py
version.py
supersqlite/__init__.py
supersqlite/idxchk.py
supersqlite.egg-info/PKG-INFO
supersqlite.egg-info/SOURCES.txt
supersqlite.egg-info/dependency_links.txt
supersqlite.egg-info/top_level.txt
supersqlite/req_wheels/.gitkeep
supersqlite/third_party/HOWTOUPGRADE.MD
supersqlite/third_party/__init__.py
supersqlite/third_party/_apsw/.gitignore
supersqlite/third_party/_apsw/LICENSE
supersqlite/third_party/_apsw/MANIFEST.in
supersqlite/third_party/_apsw/Makefile
supersqlite/third_party/_apsw/README.rst
supersqlite/third_party/_apsw/checksums
supersqlite/third_party/_apsw/example-code.py
supersqlite/third_party/_apsw/mingwsetup.bat
supersqlite/third_party/_apsw/setup.cfg
supersqlite/third_party/_apsw/setup.py
supersqlite/third_party/_apsw/tests.py
supersqlite/third_party/_apsw/doc/Makefile
supersqlite/third_party/_apsw/doc/benchmarking.rst
supersqlite/third_party/_apsw/doc/build.rst
supersqlite/third_party/_apsw/doc/changes.rst
supersqlite/third_party/_apsw/doc/conf.py
supersqlite/third_party/_apsw/doc/copyright.rst
supersqlite/third_party/_apsw/doc/dbapi.rst
supersqlite/third_party/_apsw/doc/download.rst
supersqlite/third_party/_apsw/doc/exceptions.rst
supersqlite/third_party/_apsw/doc/execution.rst
supersqlite/third_party/_apsw/doc/extensions.rst
supersqlite/third_party/_apsw/doc/index.rst
supersqlite/third_party/_apsw/doc/pysqlite.rst
supersqlite/third_party/_apsw/doc/shell.rst
supersqlite/third_party/_apsw/doc/tips.rst
supersqlite/third_party/_apsw/doc/types.rst
supersqlite/third_party/_apsw/doc/_templates/layout.html
supersqlite/third_party/_apsw/src/apsw.c
supersqlite/third_party/_apsw/src/apswbuffer.c
supersqlite/third_party/_apsw/src/apswversion.h
supersqlite/third_party/_apsw/src/backup.c
supersqlite/third_party/_apsw/src/blob.c
supersqlite/third_party/_apsw/src/connection.c
supersqlite/third_party/_apsw/src/cursor.c
supersqlite/third_party/_apsw/src/exceptions.c
supersqlite/third_party/_apsw/src/pypycompat.c
supersqlite/third_party/_apsw/src/pyutil.c
