Metadata-Version: 1.1
Name: supersqlite
Version: 0.0.78
Summary: A supercharged SQLite library for Python.
Home-page: https://gitlab.com/Plasticity/supersqlite
Author: Plasticity
Author-email: opensource@plasticity.ai
License: MIT
Keywords: supersqlite,sqlite,sqlite3,apsw,pysqlite,sql,embedded,database,db,http,remote,stream,full,text,fulltext,full-text,json,lsm,blob,vfs,fts4,fts5
Platform: UNKNOWN
Classifier: Development Status :: 5 - Production/Stable
Classifier: Intended Audience :: Developers
Classifier: Topic :: Software Development :: Libraries :: Python Modules
Classifier: Operating System :: OS Independent
Classifier: License :: OSI Approved :: MIT License
Classifier: Programming Language :: Python :: 2.7
Classifier: Programming Language :: Python :: 3
Classifier: Programming Language :: Python :: 3.0
Classifier: Programming Language :: Python :: 3.7
